bah_lol/__init__.py
bah_lol/app.py
bah_lol/cli.py
bah_lol/gas.py
bah_lol/logger.py
bah_lol/oplos.py
bah_lol/router.py
bah_lol-1.0.0.dist-info/licenses/LICENSE
bah_lol-1.0.0.dist-info/METADATA
bah_lol-1.0.0.dist-info/WHEEL
bah_lol-1.0.0.dist-info/entry_points.txt
bah_lol-1.0.0.dist-info/top_level.txt
bah_lol-1.0.0.dist-info/RECORD
