Metadata-Version: 2.4
Name: bah-lol
Version: 1.0.0
Summary: Framework API Python yang ringan, tegas, dan langsung GAS
Home-page: https://github.com/bah-lol/bah-lol
Author: Bah Lol Team
Author-email: Bah Lol Team <info@bah-lol.dev>
License: MIT
Project-URL: Homepage, https://github.com/bah-lol/bah-lol
Project-URL: Repository, https://github.com/bah-lol/bah-lol
Keywords: api,framework,web,lightweight,indonesian
Classifier: Development Status :: 4 - Beta
Classifier: Intended Audience :: Developers
Classifier: License :: OSI Approved :: MIT License
Classifier: Operating System :: OS Independent
Classifier: Programming Language :: Python :: 3
Classifier: Programming Language :: Python :: 3.7
Classifier: Programming Language :: Python :: 3.8
Classifier: Programming Language :: Python :: 3.9
Classifier: Programming Language :: Python :: 3.10
Classifier: Programming Language :: Python :: 3.11
Requires-Python: >=3.7
License-File: LICENSE
Provides-Extra: dev
Requires-Dist: pytest>=6.0; extra == "dev"
Requires-Dist: pytest-cov; extra == "dev"
Dynamic: license-file
